{"width":1024,"imagePath":"warrior_tex.png","height":1024,"name":"warrior","SubTexture":[{"width":73,"y":368,"height":33,"name":"r_l_s","x":407},{"width":47,"y":368,"height":102,"name":"r_l_b","x":283},{"width":75,"y":508,"height":116,"name":"r_l_t","x":939},{"width":73,"y":368,"height":33,"name":"l_l_s","x":332},{"width":47,"y":95,"height":102,"name":"l_l_b","x":955},{"width":75,"y":626,"height":115,"name":"l_l_t","x":939},{"width":84,"y":469,"height":60,"name":"r_fist","x":84},{"width":81,"y":469,"height":69,"name":"1","x":1},{"width":106,"y":407,"height":153,"name":"r_h","x":748},{"width":83,"y":254,"height":138,"name":"r_h_t","x":924},{"width":177,"y":1,"height":251,"name":"body","x":776},{"width":190,"y":329,"height":112,"name":"pelvis_b","x":556},{"width":158,"y":407,"height":99,"name":"pelvis_r","x":856},{"width":54,"y":1,"height":92,"name":"pelvis_l","x":955},{"width":82,"y":368,"height":104,"name":"bag","x":199},{"width":218,"y":1,"height":326,"name":"head","x":556},{"width":553,"y":1,"height":183,"name":"axe","x":1},{"width":553,"y":186,"height":180,"name":"3","x":1},{"width":97,"y":368,"height":99,"name":"l_fist","x":1},{"width":97,"y":368,"height":99,"name":"2","x":100},{"width":81,"y":508,"height":137,"name":"l_h","x":856},{"width":146,"y":254,"height":151,"name":"l_h_t","x":776}]}