{"imagePath":"stalactite_2_tex.png","width":1024,"height":512,"name":"stalactite_2","SubTexture":[{"width":228,"y":1,"height":353,"name":"Asset 2","x":347},{"width":344,"y":1,"height":234,"name":"Asset 1","x":1},{"width":36,"y":443,"height":47,"name":"s_s (4)","x":41},{"width":36,"y":434,"height":73,"name":"s_s (3)","x":163},{"width":38,"y":443,"height":48,"name":"s_s (2)","x":1},{"width":19,"y":321,"height":52,"name":"s_s (1)","x":205},{"width":104,"y":321,"height":120,"name":"b_s (5)","x":1},{"width":96,"y":321,"height":111,"name":"b_s (4)","x":107},{"width":54,"y":434,"height":74,"name":"b_s (3)","x":107},{"width":87,"y":390,"height":97,"name":"b_s (2)","x":205},{"width":70,"y":356,"height":88,"name":"b_s (1)","x":480},{"frameY":0,"y":237,"frameWidth":228,"frameHeight":83,"width":228,"height":82,"name":"s_s (7)","frameX":0,"x":1},{"width":150,"y":356,"height":75,"name":"s_s (6)","x":328},{"width":95,"y":237,"height":151,"name":"s_s (5)","x":231}]}